.gitignore
CHANGES.txt
MANIFEST.in
Makefile
README.rst
bootstrap.py
buildout-plone.cfg
buildout.cfg
setup.py
accessibility-robot/chrome.manifest
accessibility-robot/install.rdf
accessibility-robot/chrome/content/colorchecker-robot.js
accessibility-robot/chrome/content/colorchecker-robot.xul
accessibility-robot/chrome/content/wavetoolbar-robot.js
accessibility-robot/chrome/content/wavetoolbar-robot.xul
docs/conf.py
docs/contrastchecker.rst
docs/index.rst
docs/requirements.txt
docs/wavetoolbar.rst
src/Accessibility/__init__.py
src/Accessibility/accessibility.robot
src/Accessibility/contrastchecker.robot
src/Accessibility/wavetoolbar.robot
src/Accessibility/profile/extensions/accessibility@robot.xpi
src/Accessibility/profile/extensions/colorchecker@colorcheckerniquelao.net.xpi
src/Accessibility/profile/extensions/wavetoolbar@webaim.org.xpi
src/robotframework_selenium2accessibility.egg-info/PKG-INFO
src/robotframework_selenium2accessibility.egg-info/SOURCES.txt
src/robotframework_selenium2accessibility.egg-info/dependency_links.txt
src/robotframework_selenium2accessibility.egg-info/not-zip-safe
src/robotframework_selenium2accessibility.egg-info/requires.txt
src/robotframework_selenium2accessibility.egg-info/top_level.txt