Metadata-Version: 1.0
Name: robotframework-selenium2accessibility
Version: 0.2.1
Summary: Robot Framework resources for automating accessibility tools
Home-page: https://github.com/datakurre/robotframework-selenium2accessibility/
Author: Asko Soukka
Author-email: asko.soukka@iki.fi
License: GPL
Platform: UNKNOWN
Classifier: Programming Language :: Python
